transpose/__init__.py
transpose/api.py
transpose/core.py
data_transformation_tools-0.1.0.dist-info/LICENSE
data_transformation_tools-0.1.0.dist-info/METADATA
data_transformation_tools-0.1.0.dist-info/WHEEL
data_transformation_tools-0.1.0.dist-info/RECORD
