Metadata-Version: 2.1
Name: data_transformation_tools
Version: 0.1.0
Summary: Python library to data transformation
License: MIT
Author: Johnny Lazo
Author-email: johnny.lazoq@gmail.com
Requires-Python: >=3.10,<4.0
Classifier: License :: OSI Approved :: MIT License
Classifier: Programming Language :: Python
Classifier: Programming Language :: Python :: 3
Classifier: Programming Language :: Python :: 3.10
Classifier: Programming Language :: Python :: 3.11
Classifier: Programming Language :: Python :: 3.12
Requires-Dist: numpy (>=2.1.1,<3.0.0)
Requires-Dist: pyment (>=0.3.3,<0.4.0)
